wolk_gateway_module/__init__.py
wolk_gateway_module/json_data_protocol.py
wolk_gateway_module/json_firmware_update_protocol.py
wolk_gateway_module/json_registration_protocol.py
wolk_gateway_module/json_status_protocol.py
wolk_gateway_module/logger_factory.py
wolk_gateway_module/mqtt_connectivity_service.py
wolk_gateway_module/outbound_message_deque.py
wolk_gateway_module/wolk.py
wolk_gateway_module/connectivity/__init__.py
wolk_gateway_module/connectivity/connectivity_service.py
wolk_gateway_module/interface/__init__.py
wolk_gateway_module/interface/actuation_handler.py
wolk_gateway_module/interface/actuator_status_provider.py
wolk_gateway_module/interface/configuration_handler.py
wolk_gateway_module/interface/configuration_provider.py
wolk_gateway_module/interface/device_status_provider.py
wolk_gateway_module/interface/firmware_handler.py
wolk_gateway_module/interface/firmware_version_provider.py
wolk_gateway_module/model/__init__.py
wolk_gateway_module/model/actuator_command.py
wolk_gateway_module/model/actuator_state.py
wolk_gateway_module/model/actuator_status.py
wolk_gateway_module/model/actuator_template.py
wolk_gateway_module/model/alarm.py
wolk_gateway_module/model/alarm_template.py
wolk_gateway_module/model/configuration_command.py
wolk_gateway_module/model/configuration_template.py
wolk_gateway_module/model/data_type.py
wolk_gateway_module/model/device.py
wolk_gateway_module/model/device_registration_request.py
wolk_gateway_module/model/device_registration_response.py
wolk_gateway_module/model/device_registration_response_result.py
wolk_gateway_module/model/device_status.py
wolk_gateway_module/model/device_template.py
wolk_gateway_module/model/firmware_update_status.py
wolk_gateway_module/model/message.py
wolk_gateway_module/model/reading_type.py
wolk_gateway_module/model/reading_type_measurement_unit.py
wolk_gateway_module/model/reading_type_name.py
wolk_gateway_module/model/sensor_reading.py
wolk_gateway_module/model/sensor_template.py
wolk_gateway_module-1.0.9.dist-info/LICENSE
wolk_gateway_module-1.0.9.dist-info/METADATA
wolk_gateway_module-1.0.9.dist-info/WHEEL
wolk_gateway_module-1.0.9.dist-info/top_level.txt
wolk_gateway_module-1.0.9.dist-info/RECORD
