Metadata-Version: 2.1
Name: wolk-gateway-module
Version: 1.0.9
Summary: SDK for gateway communication modules that connect to WolkAbout IoT Platform
Home-page: https://github.com/Wolkabout/WolkGatewayModule-SDK-Python
Author: WolkAbout
Author-email: info@wolkabout.com
License: Apache License 2.0
Keywords: IoT,WolkAbout,Internet of Things
Platform: UNKNOWN
Classifier: Development Status :: 5 - Production/Stable
Classifier: Intended Audience :: Developers
Classifier: License :: OSI Approved :: Apache Software License
Classifier: Natural Language :: English
Classifier: Programming Language :: Python :: 3 :: Only
Classifier: Programming Language :: Python :: 3.7
Classifier: Programming Language :: Python :: 3.8
Classifier: Programming Language :: Python :: 3.9
Classifier: Operating System :: OS Independent
Classifier: Topic :: Internet
Classifier: Topic :: Communications
Classifier: Topic :: Software Development :: Embedded Systems
Requires-Python: >=3.7.0
Requires-Dist: paho-mqtt (>=1.4.0)
